panopticon/__init__.py
panopticon/compat.py
panopticon/datadog.py
panopticon/health.py
panopticon/loader.py
panopticon/django/__init__.py
panopticon/django/apps.py
panopticon/django/middleware.py
panopticon/django/urls.py
panopticon/django/views.py
python_panopticon-0.4.0.dist-info/METADATA
python_panopticon-0.4.0.dist-info/RECORD
python_panopticon-0.4.0.dist-info/WHEEL
python_panopticon-0.4.0.dist-info/top_level.txt
