Metadata-Version: 2.1
Name: python-panopticon
Version: 0.4.0
Summary: A collection of healthcheck and monitoring helpers.
Home-page: https://python-panopticon.readthedocs.org
Author: Mobify Research & Develpment Inc.
Author-email: ops@mobify.com
License: MIT
Platform: UNKNOWN
Classifier: Development Status :: 1 - Planning
Classifier: License :: OSI Approved :: MIT License
Classifier: Intended Audience :: Developers
Classifier: Programming Language :: Python
Classifier: Programming Language :: Python :: 3
Classifier: Programming Language :: Python :: 3.4
Classifier: Programming Language :: Python :: 3.5
Classifier: Programming Language :: Python :: Implementation :: CPython
Provides-Extra: dev
Provides-Extra: test
Requires-Dist: six
Requires-Dist: requests
Requires-Dist: datadog
Provides-Extra: dev
Requires-Dist: tox; extra == 'dev'
Requires-Dist: bumpversion; extra == 'dev'
Requires-Dist: twine; extra == 'dev'
Requires-Dist: wheel; extra == 'dev'
Provides-Extra: test
Requires-Dist: pytest; extra == 'test'
Requires-Dist: pytest-cache; extra == 'test'
Requires-Dist: pytest-cov; extra == 'test'
Requires-Dist: mock; extra == 'test'
